fideo_api/__init__.py
fideo_api/api_client.py
fideo_api/api_response.py
fideo_api/configuration.py
fideo_api/exceptions.py
fideo_api/py.typed
fideo_api/rest.py
fideo_api/api/__init__.py
fideo_api/api/signals_api.py
fideo_api/api/verify_api.py
fideo_api/models/__init__.py
fideo_api/models/alias.py
fideo_api/models/demographics.py
fideo_api/models/economic.py
fideo_api/models/education.py
fideo_api/models/education_date.py
fideo_api/models/email.py
fideo_api/models/employment.py
fideo_api/models/employment_date.py
fideo_api/models/evidence.py
fideo_api/models/ip_address.py
fideo_api/models/ip_country.py
fideo_api/models/location.py
fideo_api/models/location_req.py
fideo_api/models/location_type.py
fideo_api/models/multi_field_req.py
fideo_api/models/multi_field_req_with_options.py
fideo_api/models/name.py
fideo_api/models/name_with_alias.py
fideo_api/models/person_name_req.py
fideo_api/models/phone.py
fideo_api/models/photo.py
fideo_api/models/score_details.py
fideo_api/models/signals_post200_response.py
fideo_api/models/signals_response_v0.py
fideo_api/models/signals_response_v20240424.py
fideo_api/models/social_profile_details.py
fideo_api/models/social_profile_req.py
fideo_api/models/social_profile_urls.py
fideo_api/models/verify_response.py
fideo_api-1.0.4.dist-info/LICENSE
fideo_api-1.0.4.dist-info/METADATA
fideo_api-1.0.4.dist-info/WHEEL
fideo_api-1.0.4.dist-info/top_level.txt
fideo_api-1.0.4.dist-info/RECORD
