Metadata-Version: 2.1
Name: fideo-api
Version: 1.0.4
Summary: Fideo API
Home-page: 
Author: OpenAPI Generator community
Author-email: support@fideo.ai
License: Apache 2.0
Keywords: OpenAPI,OpenAPI-Generator,Fideo API
License-File: LICENSE
Requires-Dist: urllib3<2.1.0,>=1.25.3
Requires-Dist: python-dateutil
Requires-Dist: pydantic>=2
Requires-Dist: typing-extensions>=4.7.1
